{
	"name": "Excel1",
	"properties": {
		"linkedServiceName": {
			"referenceName": "AzureBlobStorage2",
			"type": "LinkedServiceReference"
		},
		"parameters": {
			"Excel1": {
				"type": "string",
				"defaultValue": "  "
			}
		},
		"annotations": [],
		"type": "Excel",
		"typeProperties": {
			"location": {
				"type": "AzureBlobStorageLocation",
				"fileName": "dataset().filename",
				"folderPath": "dataset().directory",
				"container": "dataset().container"
			},
			"firstRowAsHeader": false
		},
		"schema": []
	}
}